{
  "hash": "833c3956",
  "configHash": "91805586",
  "lockfileHash": "b587530a",
  "browserHash": "b8fbec83",
  "optimized": {
    "react": {
      "src": "../../node_modules/react/index.js",
      "file": "react.js",
      "fileHash": "022d0f0e",
      "needsInterop": true
    },
    "react-dom": {
      "src": "../../node_modules/react-dom/index.js",
      "file": "react-dom.js",
      "fileHash": "bd840614",
      "needsInterop": true
    },
    "react/jsx-dev-runtime": {
      "src": "../../node_modules/react/jsx-dev-runtime.js",
      "file": "react_jsx-dev-runtime.js",
      "fileHash": "af242e6b",
      "needsInterop": true
    },
    "react/jsx-runtime": {
      "src": "../../node_modules/react/jsx-runtime.js",
      "file": "react_jsx-runtime.js",
      "fileHash": "a71c66f5",
      "needsInterop": true
    }
  },
  "chunks": {
    "chunk-5HG46X4L": {
      "file": "chunk-5HG46X4L.js"
    }
  }
}